odoo/addons/account_reporting_weight/README.rst
odoo/addons/account_reporting_weight/__init__.py
odoo/addons/account_reporting_weight/__manifest__.py
odoo/addons/account_reporting_weight/i18n/account_reporting_weight.pot
odoo/addons/account_reporting_weight/i18n/de.po
odoo/addons/account_reporting_weight/i18n/es.po
odoo/addons/account_reporting_weight/i18n/fr.po
odoo/addons/account_reporting_weight/i18n/hr_HR.po
odoo/addons/account_reporting_weight/i18n/id.po
odoo/addons/account_reporting_weight/i18n/it.po
odoo/addons/account_reporting_weight/i18n/sl.po
odoo/addons/account_reporting_weight/i18n/tr.po
odoo/addons/account_reporting_weight/readme/CONFIGURE.rst
odoo/addons/account_reporting_weight/readme/CONTRIBUTORS.rst
odoo/addons/account_reporting_weight/readme/DESCRIPTION.rst
odoo/addons/account_reporting_weight/readme/INSTALL.rst
odoo/addons/account_reporting_weight/readme/USAGE.rst
odoo/addons/account_reporting_weight/reports/__init__.py
odoo/addons/account_reporting_weight/reports/account_invoice_report.py
odoo/addons/account_reporting_weight/static/description/icon.png
odoo/addons/account_reporting_weight/static/description/index.html
odoo11_addon_account_reporting_weight-11.0.1.0.0.99.dev7.dist-info/METADATA
odoo11_addon_account_reporting_weight-11.0.1.0.0.99.dev7.dist-info/WHEEL
odoo11_addon_account_reporting_weight-11.0.1.0.0.99.dev7.dist-info/top_level.txt
odoo11_addon_account_reporting_weight-11.0.1.0.0.99.dev7.dist-info/RECORD
